smcp/__init__.py
smcp/_version.py
smcp/analysis.py
smcp/base.py
smcp/misc.cp36-win_amd64.pyd
smcp/solvers.py
smcp-0.4.6.dist-info/METADATA
smcp-0.4.6.dist-info/RECORD
smcp-0.4.6.dist-info/WHEEL
smcp-0.4.6.dist-info/top_level.txt
