Metadata-Version: 2.0
Name: smcp
Version: 0.4.6
Summary: Python extension for solving sparse matrix cone programs
Home-page: http://cvxopt.github.io/smcp
Author: Martin S. Andersen and Lieven Vandenberghe
Author-email: martin.skovgaard.andersen@gmail.com, vandenbe@ee.ucla.edu
License: GNU GPL version 3
Platform: UNKNOWN
Requires-Dist: chompack (>=2.3.2)
Requires-Dist: cvxopt (>=1.1.9)
